MANIFEST.in
README.txt
VERSION.txt
setup.py
src/scripts/telephonied
src/telephonie/__init__.py
src/telephonie.egg-info/PKG-INFO
src/telephonie.egg-info/SOURCES.txt
src/telephonie.egg-info/dependency_links.txt
src/telephonie.egg-info/not-zip-safe
src/telephonie.egg-info/requires.txt
src/telephonie.egg-info/top_level.txt
src/telephonie/core/__init__.py
src/telephonie/core/commands.py
src/telephonie/core/errors.py
src/telephonie/core/eventsocket.py
src/telephonie/core/eventtypes.py
src/telephonie/core/inboundsocket.py
src/telephonie/core/outboundsocket.py
src/telephonie/core/transport.py
src/telephonie/utils/__init__.py
src/telephonie/utils/daemonize.py
src/telephonie/utils/logger.py
src/tests/__init__.py
src/tests/test_events.py
src/tests/test_inboundsocket.py