Metadata-Version: 1.0
Name: telephonie
Version: 0.3.1
Summary: Telephonie framework
Home-page: http://github.com/miglu/Telephonie
Author: Telephonie Team
Author-email: telephonie@miglu.com
License: MPL 1.1
Keywords: telecom voip telephony freeswitch ivr
Platform: linux
Classifier: Programming Language :: Python
Classifier: Operating System :: POSIX
Classifier: Topic :: Internet
Classifier: Topic :: Software Development :: Libraries :: Python Modules
Classifier: Topic :: Communications
Classifier: Topic :: Multimedia
Classifier: Environment :: Console
Classifier: Environment :: Web Environment
Classifier: Programming Language :: Python
Classifier: Intended Audience :: Developers
Classifier: Intended Audience :: Telecommunications Industry
Classifier: License :: OSI Approved :: Mozilla Public License 1.1 (MPL 1.1)
Classifier: Development Status :: 4 - Beta
